Workbook

Sheet Инструкция
A1: Учёт доходов и расходов малого бизнеса
A3: Для кого: начинающий бизнес, ИП, салон, кафе, студия, магазин — все, кто хочет видеть, куда уходят деньги.
A4: 1. «Операции»: каждое поступление или трата — одна строка. Тип и статью выбирай из списка.
A5: 2. «Статьи»: можешь поменять или добавить свои статьи доходов и расходов.
A6: 3. «Сводка»: доходы, расходы и прибыль по месяцам — считается сама. Меняй год в жёлтой ячейке.
A7: В примере — условные операции, удали их и вноси свои.

Sheet Статьи
A1: Тип | B1: Статья
A2: Доход | B2: Продажи
A3: Доход | B3: Услуги
A4: Доход | B4: Прочие доходы
A5: Расход | B5: Закупка товара / сырья
A6: Расход | B6: Аренда
A7: Расход | B7: Зарплата
A8: Расход | B8: Реклама
A9: Расход | B9: Налоги
A10: Расход | B10: Связь и сервисы
A11: Расход | B11: Транспорт и доставка
A12: Расход | B12: Прочие расходы

Sheet Операции
A1: Дата | B1: Тип | C1: Статья | D1: Сумма | E1: Комментарий | F1: Месяц
A2: 46266 | B2: Доход | C2: Продажи | D2: 85000 | E2: Выручка за неделю | F2: =IF(A2="","",YEAR(A2)&"-"&TEXT(MONTH(A2),"00"))
A3: 46267 | B3: Расход | C3: Аренда | D3: 20000 | E3: Сентябрь | F3: =IF(A3="","",YEAR(A3)&"-"&TEXT(MONTH(A3),"00"))
A4: 46270 | B4: Расход | C4: Реклама | D4: 7000 | E4: Таргет Instagram | F4: =IF(A4="","",YEAR(A4)&"-"&TEXT(MONTH(A4),"00"))
A5: 46273 | B5: Доход | C5: Услуги | D5: 15000 | F5: =IF(A5="","",YEAR(A5)&"-"&TEXT(MONTH(A5),"00"))
F6: =IF(A6="","",YEAR(A6)&"-"&TEXT(MONTH(A6),"00"))
F7: =IF(A7="","",YEAR(A7)&"-"&TEXT(MONTH(A7),"00"))
F8: =IF(A8="","",YEAR(A8)&"-"&TEXT(MONTH(A8),"00"))
F9: =IF(A9="","",YEAR(A9)&"-"&TEXT(MONTH(A9),"00"))
F10: =IF(A10="","",YEAR(A10)&"-"&TEXT(MONTH(A10),"00"))
F11: =IF(A11="","",YEAR(A11)&"-"&TEXT(MONTH(A11),"00"))
F12: =IF(A12="","",YEAR(A12)&"-"&TEXT(MONTH(A12),"00"))
F13: =IF(A13="","",YEAR(A13)&"-"&TEXT(MONTH(A13),"00"))
F14: =IF(A14="","",YEAR(A14)&"-"&TEXT(MONTH(A14),"00"))
F15: =IF(A15="","",YEAR(A15)&"-"&TEXT(MONTH(A15),"00"))
F16: =IF(A16="","",YEAR(A16)&"-"&TEXT(MONTH(A16),"00"))
F17: =IF(A17="","",YEAR(A17)&"-"&TEXT(MONTH(A17),"00"))
... F2000: =IF(A2000="","",YEAR(A2000)&"-"&TEXT(MONTH(A2000),"00"))

Sheet Сводка
A1: Сводка по месяцам
A2: Год | B2: 2026
A4: Месяц | B4: Доходы | C4: Расходы | D4: Прибыль | E4: Рентабельность
A5: =$B$2&"-"&TEXT(1,"00") | B5: =SUMIFS(Операции!$D$2:$D$2000,Операции!$F$2:$F$2000,A5,Операции!$B$2:$B$2000,"Доход") | C5: =SUMIFS(Операции!$D$2:$D$2000,Операции!$F$2:$F$2000,A5,Операции!$B$2:$B$2000,"Расход") | D5: =B5-C5 | E5: =IF(B5>0,D5/B5,0)
A6: =$B$2&"-"&TEXT(2,"00") | B6: =SUMIFS(Операции!$D$2:$D$2000,Операции!$F$2:$F$2000,A6,Операции!$B$2:$B$2000,"Доход") | C6: =SUMIFS(Операции!$D$2:$D$2000,Операции!$F$2:$F$2000,A6,Операции!$B$2:$B$2000,"Расход") | D6: =B6-C6 | E6: =IF(B6>0,D6/B6,0)
A7: =$B$2&"-"&TEXT(3,"00") | B7: =SUMIFS(Операции!$D$2:$D$2000,Операции!$F$2:$F$2000,A7,Операции!$B$2:$B$2000,"Доход") | C7: =SUMIFS(Операции!$D$2:$D$2000,Операции!$F$2:$F$2000,A7,Операции!$B$2:$B$2000,"Расход") | D7: =B7-C7 | E7: =IF(B7>0,D7/B7,0)
A8: =$B$2&"-"&TEXT(4,"00") | B8: =SUMIFS(Операции!$D$2:$D$2000,Операции!$F$2:$F$2000,A8,Операции!$B$2:$B$2000,"Доход") | C8: =SUMIFS(Операции!$D$2:$D$2000,Операции!$F$2:$F$2000,A8,Операции!$B$2:$B$2000,"Расход") | D8: =B8-C8 | E8: =IF(B8>0,D8/B8,0)
A9: =$B$2&"-"&TEXT(5,"00") | B9: =SUMIFS(Операции!$D$2:$D$2000,Операции!$F$2:$F$2000,A9,Операции!$B$2:$B$2000,"Доход") | C9: =SUMIFS(Операции!$D$2:$D$2000,Операции!$F$2:$F$2000,A9,Операции!$B$2:$B$2000,"Расход") | D9: =B9-C9 | E9: =IF(B9>0,D9/B9,0)
A10: =$B$2&"-"&TEXT(6,"00") | B10: =SUMIFS(Операции!$D$2:$D$2000,Операции!$F$2:$F$2000,A10,Операции!$B$2:$B$2000,"Доход") | C10: =SUMIFS(Операции!$D$2:$D$2000,Операции!$F$2:$F$2000,A10,Операции!$B$2:$B$2000,"Расход") | D10: =B10-C10 | E10: =IF(B10>0,D10/B10,0)
A11: =$B$2&"-"&TEXT(7,"00") | B11: =SUMIFS(Операции!$D$2:$D$2000,Операции!$F$2:$F$2000,A11,Операции!$B$2:$B$2000,"Доход") | C11: =SUMIFS(Операции!$D$2:$D$2000,Операции!$F$2:$F$2000,A11,Операции!$B$2:$B$2000,"Расход") | D11: =B11-C11 | E11: =IF(B11>0,D11/B11,0)
A12: =$B$2&"-"&TEXT(8,"00") | B12: =SUMIFS(Операции!$D$2:$D$2000,Операции!$F$2:$F$2000,A12,Операции!$B$2:$B$2000,"Доход") | C12: =SUMIFS(Операции!$D$2:$D$2000,Операции!$F$2:$F$2000,A12,Операции!$B$2:$B$2000,"Расход") | D12: =B12-C12 | E12: =IF(B12>0,D12/B12,0)
A13: =$B$2&"-"&TEXT(9,"00") | B13: =SUMIFS(Операции!$D$2:$D$2000,Операции!$F$2:$F$2000,A13,Операции!$B$2:$B$2000,"Доход") | C13: =SUMIFS(Операции!$D$2:$D$2000,Операции!$F$2:$F$2000,A13,Операции!$B$2:$B$2000,"Расход") | D13: =B13-C13 | E13: =IF(B13>0,D13/B13,0)
A14: =$B$2&"-"&TEXT(10,"00") | B14: =SUMIFS(Операции!$D$2:$D$2000,Операции!$F$2:$F$2000,A14,Операции!$B$2:$B$2000,"Доход") | C14: =SUMIFS(Операции!$D$2:$D$2000,Операции!$F$2:$F$2000,A14,Операции!$B$2:$B$2000,"Расход") | D14: =B14-C14 | E14: =IF(B14>0,D14/B14,0)
A15: =$B$2&"-"&TEXT(11,"00") | B15: =SUMIFS(Операции!$D$2:$D$2000,Операции!$F$2:$F$2000,A15,Операции!$B$2:$B$2000,"Доход") | C15: =SUMIFS(Операции!$D$2:$D$2000,Операции!$F$2:$F$2000,A15,Операции!$B$2:$B$2000,"Расход") | D15: =B15-C15 | E15: =IF(B15>0,D15/B15,0)
A16: =$B$2&"-"&TEXT(12,"00") | B16: =SUMIFS(Операции!$D$2:$D$2000,Операции!$F$2:$F$2000,A16,Операции!$B$2:$B$2000,"Доход") | C16: =SUMIFS(Операции!$D$2:$D$2000,Операции!$F$2:$F$2000,A16,Операции!$B$2:$B$2000,"Расход") | D16: =B16-C16 | E16: =IF(B16>0,D16/B16,0)
A17: Итого за год | B17: =SUM(B5:B16) | C17: =SUM(C5:C16) | D17: =SUM(D5:D16) | E17: =IF(B17>0,D17/B17,0)
A19: Расходы по статьям за год | B19: Сумма
A20: =IF(INDEX(Статьи!$A$2:$A$40,4)="Расход",INDEX(Статьи!$B$2:$B$40,4),"") | B20: =IF(A20="","",SUMIFS(Операции!$D$2:$D$2000,Операции!$C$2:$C$2000,A20,Операции!$F$2:$F$2000,$B$2&"-*"))
A21: =IF(INDEX(Статьи!$A$2:$A$40,5)="Расход",INDEX(Статьи!$B$2:$B$40,5),"") | B21: =IF(A21="","",SUMIFS(Операции!$D$2:$D$2000,Операции!$C$2:$C$2000,A21,Операции!$F$2:$F$2000,$B$2&"-*"))
A22: =IF(INDEX(Статьи!$A$2:$A$40,6)="Расход",INDEX(Статьи!$B$2:$B$40,6),"") | B22: =IF(A22="","",SUMIFS(Операции!$D$2:$D$2000,Операции!$C$2:$C$2000,A22,Операции!$F$2:$F$2000,$B$2&"-*"))
A23: =IF(INDEX(Статьи!$A$2:$A$40,7)="Расход",INDEX(Статьи!$B$2:$B$40,7),"") | B23: =IF(A23="","",SUMIFS(Операции!$D$2:$D$2000,Операции!$C$2:$C$2000,A23,Операции!$F$2:$F$2000,$B$2&"-*"))
A24: =IF(INDEX(Статьи!$A$2:$A$40,8)="Расход",INDEX(Статьи!$B$2:$B$40,8),"") | B24: =IF(A24="","",SUMIFS(Операции!$D$2:$D$2000,Операции!$C$2:$C$2000,A24,Операции!$F$2:$F$2000,$B$2&"-*"))
A25: =IF(INDEX(Статьи!$A$2:$A$40,9)="Расход",INDEX(Статьи!$B$2:$B$40,9),"") | B25: =IF(A25="","",SUMIFS(Операции!$D$2:$D$2000,Операции!$C$2:$C$2000,A25,Операции!$F$2:$F$2000,$B$2&"-*"))
A26: =IF(INDEX(Статьи!$A$2:$A$40,10)="Расход",INDEX(Статьи!$B$2:$B$40,10),"") | B26: =IF(A26="","",SUMIFS(Операции!$D$2:$D$2000,Операции!$C$2:$C$2000,A26,Операции!$F$2:$F$2000,$B$2&"-*"))
A27: =IF(INDEX(Статьи!$A$2:$A$40,11)="Расход",INDEX(Статьи!$B$2:$B$40,11),"") | B27: =IF(A27="","",SUMIFS(Операции!$D$2:$D$2000,Операции!$C$2:$C$2000,A27,Операции!$F$2:$F$2000,$B$2&"-*"))
A28: =IF(INDEX(Статьи!$A$2:$A$40,12)="Расход",INDEX(Статьи!$B$2:$B$40,12),"") | B28: =IF(A28="","",SUMIFS(Операции!$D$2:$D$2000,Операции!$C$2:$C$2000,A28,Операции!$F$2:$F$2000,$B$2&"-*"))
A29: =IF(INDEX(Статьи!$A$2:$A$40,13)="Расход",INDEX(Статьи!$B$2:$B$40,13),"") | B29: =IF(A29="","",SUMIFS(Операции!$D$2:$D$2000,Операции!$C$2:$C$2000,A29,Операции!$F$2:$F$2000,$B$2&"-*"))
