Workbook

Sheet Инструкция
A1: Калькулятор себестоимости и наценки
A3: Для кого: производство, общепит, торговля, маркетплейсы, услуги — любой товар или услуга.
A4: 1. Лист «Калькулятор»: заполняй только жёлтые ячейки с синим текстом. Остальное считается само.
A5: 2. Сначала — затраты на единицу (сырьё, упаковка, работа, доставка). Потом — постоянные расходы в месяц и план продаж.
A6: 3. Укажи желаемую наценку — таблица покажет цену, прибыль с единицы и точку безубыточности.
A7: 4. Можно менять любые формулы под себя: Файл → Создать копию, и таблица твоя.
A8: 5. Лист «Сравнение цен» — проверить 3 варианта цены за раз.
A9: Наценка = (цена − себестоимость) / себестоимость. Маржа = (цена − себестоимость) / цена. Это разные вещи — таблица считает обе.
A10: В примере заполнены условные цифры — замени их своими.

Sheet Калькулятор
A1: Калькулятор себестоимости и наценки
A2: Жёлтые ячейки — заполняешь ты. Суммы в сомах (можно в любой валюте, главное — одной).
A4: Переменные затраты на 1 единицу | B4: Сумма
A5: Сырьё / закупочная цена товара | B5: 350
A6: Упаковка | B6: 25
A7: Работа (сдельная оплата за единицу) | B7: 60
A8: Доставка до склада / клиента за единицу | B8: 40
A9: Комиссия маркетплейса / эквайринга, % от цены | B9: 0.1
A10: Прочее на единицу | B10: 0
A11: Переменные затраты без комиссии, на единицу | B11: =B5+B6+B7+B8+B10
A13: Постоянные расходы в месяц | B13: Сумма
A14: Аренда | B14: 20000
A15: Зарплата (оклады) | B15: 40000
A16: Реклама | B16: 15000
A17: Связь, интернет, сервисы | B17: 3000
A18: Налоги и бухгалтерия (фикс.) | B18: 5000
A19: Прочее | B19: 2000
A20: Итого постоянные в месяц | B20: =SUM(B14:B19)
A21: План продаж, единиц в месяц | B21: 300
A22: Постоянные расходы на 1 единицу | B22: =IF(B21>0,B20/B21,0)
A23: Полная себестоимость единицы (без комиссии) | B23: =B11+B22
A25: Цена и прибыль | B25: Значение
A26: Желаемая наценка на полную себестоимость | B26: 0.8
A27: Рекомендованная цена (с учётом комиссии) | B27: =IF(B9<1,B23*(1+B26)/(1-B9),0)
A28: Твоя цена (если хочешь проверить свою) | B28: 1200
A29: Комиссия с единицы по твоей цене | B29: =B28*B9
A30: Прибыль с единицы по твоей цене | B30: =B28-B23-B29
A31: Наценка по твоей цене | B31: =IF(B23>0,(B28-B23)/B23,0)
A32: Маржа по твоей цене (после комиссии) | B32: =IF(B28>0,B30/B28,0)
A33: Прибыль в месяц при плане продаж | B33: =B30*B21
A34: Точка безубыточности, единиц в месяц | B34: =IF(B28-B11-B29>0,ROUNDUP(B20/(B28-B11-B29),0),"цена ниже затрат")

Sheet Сравнение цен
A1: Сравнение трёх вариантов цены
A3: Показатель | B3: Вариант 1 | C3: Вариант 2 | D3: Вариант 3
A4: Цена | B4: 900 | C4: 1200 | D4: 1500
A5: Ожидаемые продажи в месяц, единиц | B5: 400 | C5: 300 | D5: 200
A6: Переменные + комиссия на единицу | B6: =B4*Калькулятор!$B$9+Калькулятор!$B$11 | C6: =C4*Калькулятор!$B$9+Калькулятор!$B$11 | D6: =D4*Калькулятор!$B$9+Калькулятор!$B$11
A7: Прибыль с единицы до постоянных | B7: =B4-B6 | C7: =C4-C6 | D7: =D4-D6
A8: Прибыль в месяц | B8: =B7*B5-Калькулятор!$B$20 | C8: =C7*C5-Калькулятор!$B$20 | D8: =D7*D5-Калькулятор!$B$20
A9: Точка безубыточности, единиц | B9: =IF(B7>0,ROUNDUP(Калькулятор!$B$20/B7,0),"убыток") | C9: =IF(C7>0,ROUNDUP(Калькулятор!$B$20/C7,0),"убыток") | D9: =IF(D7>0,ROUNDUP(Калькулятор!$B$20/D7,0),"убыток")
