Workbook

Sheet Инструкция
A1: Учёт продаж и юнит-экономика для продавца маркетплейса
A3: Для кого: продавцы Wildberries, Ozon, Lalafo, Instagram-магазины — любой, кто продаёт товары онлайн.
A4: 1. «Товары»: один раз заполни карточки — артикул, закупка, комиссия площадки, логистика. Таблица посчитает прибыль с единицы и маржу.
A5: 2. «Продажи»: каждая продажа или возврат — одна строка. Артикул выбирай из списка, остальное подтянется само.
A6: 3. «Остатки»: приход товара вносишь сюда — остаток = приход − продано + возвраты.
A7: 4. «Итоги»: выручка, прибыль, возвраты по месяцам — меняй месяц в жёлтой ячейке.
A8: Комиссии и тарифы площадок меняются — сверяй их в личном кабинете продавца. В примере цифры условные.

Sheet Товары
A1: Артикул | B1: Название | C1: Закупка за шт | D1: Доставка до склада за шт | E1: Упаковка/маркировка за шт | F1: Цена продажи | G1: Комиссия площадки, % | H1: Логистика площадки за шт | I1: Налог, % от цены | J1: Прибыль с шт | K1: Маржа
A2: A-001 | B2: Термокружка 450 мл | C2: 320 | D2: 30 | E2: 15 | F2: 990 | G2: 0.19 | H2: 60 | I2: 0.04 | J2: =IF(A2="","",F2-C2-D2-E2-F2*G2-H2-F2*I2) | K2: =IF(OR(A2="",F2=0),"",J2/F2)
A3: A-002 | B3: Органайзер для кухни | C3: 210 | D3: 25 | E3: 10 | F3: 690 | G3: 0.19 | H3: 55 | I3: 0.04 | J3: =IF(A3="","",F3-C3-D3-E3-F3*G3-H3-F3*I3) | K3: =IF(OR(A3="",F3=0),"",J3/F3)
A4: A-003 | B4: Набор полотенец | C4: 540 | D4: 40 | E4: 20 | F4: 1590 | G4: 0.19 | H4: 80 | I4: 0.04 | J4: =IF(A4="","",F4-C4-D4-E4-F4*G4-H4-F4*I4) | K4: =IF(OR(A4="",F4=0),"",J4/F4)
J5: =IF(A5="","",F5-C5-D5-E5-F5*G5-H5-F5*I5) | K5: =IF(OR(A5="",F5=0),"",J5/F5)
J6: =IF(A6="","",F6-C6-D6-E6-F6*G6-H6-F6*I6) | K6: =IF(OR(A6="",F6=0),"",J6/F6)
J7: =IF(A7="","",F7-C7-D7-E7-F7*G7-H7-F7*I7) | K7: =IF(OR(A7="",F7=0),"",J7/F7)
J8: =IF(A8="","",F8-C8-D8-E8-F8*G8-H8-F8*I8) | K8: =IF(OR(A8="",F8=0),"",J8/F8)
J9: =IF(A9="","",F9-C9-D9-E9-F9*G9-H9-F9*I9) | K9: =IF(OR(A9="",F9=0),"",J9/F9)
J10: =IF(A10="","",F10-C10-D10-E10-F10*G10-H10-F10*I10) | K10: =IF(OR(A10="",F10=0),"",J10/F10)
J11: =IF(A11="","",F11-C11-D11-E11-F11*G11-H11-F11*I11) | K11: =IF(OR(A11="",F11=0),"",J11/F11)
J12: =IF(A12="","",F12-C12-D12-E12-F12*G12-H12-F12*I12) | K12: =IF(OR(A12="",F12=0),"",J12/F12)
J13: =IF(A13="","",F13-C13-D13-E13-F13*G13-H13-F13*I13) | K13: =IF(OR(A13="",F13=0),"",J13/F13)
J14: =IF(A14="","",F14-C14-D14-E14-F14*G14-H14-F14*I14) | K14: =IF(OR(A14="",F14=0),"",J14/F14)
J15: =IF(A15="","",F15-C15-D15-E15-F15*G15-H15-F15*I15) | K15: =IF(OR(A15="",F15=0),"",J15/F15)
J16: =IF(A16="","",F16-C16-D16-E16-F16*G16-H16-F16*I16) | K16: =IF(OR(A16="",F16=0),"",J16/F16)
... J51: =IF(A51="","",F51-C51-D51-E51-F51*G51-H51-F51*I51) | K51: =IF(OR(A51="",F51=0),"",J51/F51)

Sheet Продажи
A1: Дата | B1: Артикул | C1: Кол-во (возврат — минус) | D1: Цена продажи за шт | E1: Выручка | F1: Прибыль | G1: Месяц
A2: 46266 | B2: A-001 | C2: 2 | D2: =IF(B2="","",IFERROR(INDEX(Товары!$F$2:$F$51,MATCH(B2,Товары!$A$2:$A$51,0)),"")) | E2: =IF(OR(B2="",D2=""),"",C2*D2) | F2: =IF(B2="","",IFERROR(C2*INDEX(Товары!$J$2:$J$51,MATCH(B2,Товары!$A$2:$A$51,0)),"")) | G2: =IF(A2="","",YEAR(A2)&"-"&TEXT(MONTH(A2),"00"))
A3: 46267 | B3: A-003 | C3: 1 | D3: =IF(B3="","",IFERROR(INDEX(Товары!$F$2:$F$51,MATCH(B3,Товары!$A$2:$A$51,0)),"")) | E3: =IF(OR(B3="",D3=""),"",C3*D3) | F3: =IF(B3="","",IFERROR(C3*INDEX(Товары!$J$2:$J$51,MATCH(B3,Товары!$A$2:$A$51,0)),"")) | G3: =IF(A3="","",YEAR(A3)&"-"&TEXT(MONTH(A3),"00"))
A4: 46268 | B4: A-002 | C4: 3 | D4: =IF(B4="","",IFERROR(INDEX(Товары!$F$2:$F$51,MATCH(B4,Товары!$A$2:$A$51,0)),"")) | E4: =IF(OR(B4="",D4=""),"",C4*D4) | F4: =IF(B4="","",IFERROR(C4*INDEX(Товары!$J$2:$J$51,MATCH(B4,Товары!$A$2:$A$51,0)),"")) | G4: =IF(A4="","",YEAR(A4)&"-"&TEXT(MONTH(A4),"00"))
A5: 46270 | B5: A-001 | C5: -1 | D5: =IF(B5="","",IFERROR(INDEX(Товары!$F$2:$F$51,MATCH(B5,Товары!$A$2:$A$51,0)),"")) | E5: =IF(OR(B5="",D5=""),"",C5*D5) | F5: =IF(B5="","",IFERROR(C5*INDEX(Товары!$J$2:$J$51,MATCH(B5,Товары!$A$2:$A$51,0)),"")) | G5: =IF(A5="","",YEAR(A5)&"-"&TEXT(MONTH(A5),"00"))
D6: =IF(B6="","",IFERROR(INDEX(Товары!$F$2:$F$51,MATCH(B6,Товары!$A$2:$A$51,0)),"")) | E6: =IF(OR(B6="",D6=""),"",C6*D6) | F6: =IF(B6="","",IFERROR(C6*INDEX(Товары!$J$2:$J$51,MATCH(B6,Товары!$A$2:$A$51,0)),"")) | G6: =IF(A6="","",YEAR(A6)&"-"&TEXT(MONTH(A6),"00"))
D7: =IF(B7="","",IFERROR(INDEX(Товары!$F$2:$F$51,MATCH(B7,Товары!$A$2:$A$51,0)),"")) | E7: =IF(OR(B7="",D7=""),"",C7*D7) | F7: =IF(B7="","",IFERROR(C7*INDEX(Товары!$J$2:$J$51,MATCH(B7,Товары!$A$2:$A$51,0)),"")) | G7: =IF(A7="","",YEAR(A7)&"-"&TEXT(MONTH(A7),"00"))
D8: =IF(B8="","",IFERROR(INDEX(Товары!$F$2:$F$51,MATCH(B8,Товары!$A$2:$A$51,0)),"")) | E8: =IF(OR(B8="",D8=""),"",C8*D8) | F8: =IF(B8="","",IFERROR(C8*INDEX(Товары!$J$2:$J$51,MATCH(B8,Товары!$A$2:$A$51,0)),"")) | G8: =IF(A8="","",YEAR(A8)&"-"&TEXT(MONTH(A8),"00"))
D9: =IF(B9="","",IFERROR(INDEX(Товары!$F$2:$F$51,MATCH(B9,Товары!$A$2:$A$51,0)),"")) | E9: =IF(OR(B9="",D9=""),"",C9*D9) | F9: =IF(B9="","",IFERROR(C9*INDEX(Товары!$J$2:$J$51,MATCH(B9,Товары!$A$2:$A$51,0)),"")) | G9: =IF(A9="","",YEAR(A9)&"-"&TEXT(MONTH(A9),"00"))
D10: =IF(B10="","",IFERROR(INDEX(Товары!$F$2:$F$51,MATCH(B10,Товары!$A$2:$A$51,0)),"")) | E10: =IF(OR(B10="",D10=""),"",C10*D10) | F10: =IF(B10="","",IFERROR(C10*INDEX(Товары!$J$2:$J$51,MATCH(B10,Товары!$A$2:$A$51,0)),"")) | G10: =IF(A10="","",YEAR(A10)&"-"&TEXT(MONTH(A10),"00"))
D11: =IF(B11="","",IFERROR(INDEX(Товары!$F$2:$F$51,MATCH(B11,Товары!$A$2:$A$51,0)),"")) | E11: =IF(OR(B11="",D11=""),"",C11*D11) | F11: =IF(B11="","",IFERROR(C11*INDEX(Товары!$J$2:$J$51,MATCH(B11,Товары!$A$2:$A$51,0)),"")) | G11: =IF(A11="","",YEAR(A11)&"-"&TEXT(MONTH(A11),"00"))
D12: =IF(B12="","",IFERROR(INDEX(Товары!$F$2:$F$51,MATCH(B12,Товары!$A$2:$A$51,0)),"")) | E12: =IF(OR(B12="",D12=""),"",C12*D12) | F12: =IF(B12="","",IFERROR(C12*INDEX(Товары!$J$2:$J$51,MATCH(B12,Товары!$A$2:$A$51,0)),"")) | G12: =IF(A12="","",YEAR(A12)&"-"&TEXT(MONTH(A12),"00"))
D13: =IF(B13="","",IFERROR(INDEX(Товары!$F$2:$F$51,MATCH(B13,Товары!$A$2:$A$51,0)),"")) | E13: =IF(OR(B13="",D13=""),"",C13*D13) | F13: =IF(B13="","",IFERROR(C13*INDEX(Товары!$J$2:$J$51,MATCH(B13,Товары!$A$2:$A$51,0)),"")) | G13: =IF(A13="","",YEAR(A13)&"-"&TEXT(MONTH(A13),"00"))
D14: =IF(B14="","",IFERROR(INDEX(Товары!$F$2:$F$51,MATCH(B14,Товары!$A$2:$A$51,0)),"")) | E14: =IF(OR(B14="",D14=""),"",C14*D14) | F14: =IF(B14="","",IFERROR(C14*INDEX(Товары!$J$2:$J$51,MATCH(B14,Товары!$A$2:$A$51,0)),"")) | G14: =IF(A14="","",YEAR(A14)&"-"&TEXT(MONTH(A14),"00"))
D15: =IF(B15="","",IFERROR(INDEX(Товары!$F$2:$F$51,MATCH(B15,Товары!$A$2:$A$51,0)),"")) | E15: =IF(OR(B15="",D15=""),"",C15*D15) | F15: =IF(B15="","",IFERROR(C15*INDEX(Товары!$J$2:$J$51,MATCH(B15,Товары!$A$2:$A$51,0)),"")) | G15: =IF(A15="","",YEAR(A15)&"-"&TEXT(MONTH(A15),"00"))
D16: =IF(B16="","",IFERROR(INDEX(Товары!$F$2:$F$51,MATCH(B16,Товары!$A$2:$A$51,0)),"")) | E16: =IF(OR(B16="",D16=""),"",C16*D16) | F16: =IF(B16="","",IFERROR(C16*INDEX(Товары!$J$2:$J$51,MATCH(B16,Товары!$A$2:$A$51,0)),"")) | G16: =IF(A16="","",YEAR(A16)&"-"&TEXT(MONTH(A16),"00"))
D17: =IF(B17="","",IFERROR(INDEX(Товары!$F$2:$F$51,MATCH(B17,Товары!$A$2:$A$51,0)),"")) | E17: =IF(OR(B17="",D17=""),"",C17*D17) | F17: =IF(B17="","",IFERROR(C17*INDEX(Товары!$J$2:$J$51,MATCH(B17,Товары!$A$2:$A$51,0)),"")) | G17: =IF(A17="","",YEAR(A17)&"-"&TEXT(MONTH(A17),"00"))
... D1000: =IF(B1000="","",IFERROR(INDEX(Товары!$F$2:$F$51,MATCH(B1000,Товары!$A$2:$A$51,0)),"")) | E1000: =IF(OR(B1000="",D1000=""),"",C1000*D1000) | F1000: =IF(B1000="","",IFERROR(C1000*INDEX(Товары!$J$2:$J$51,MATCH(B1000,Товары!$A$2:$A$51,0)),"")) | G1000: =IF(A1000="","",YEAR(A1000)&"-"&TEXT(MONTH(A1000),"00"))

Sheet Остатки
A1: Артикул | B1: Приход, шт | C1: Продано (с учётом возвратов) | D1: Остаток | E1: Заказать, если меньше | F1: Сигнал
A2: =IF(Товары!A2="","",Товары!A2) | B2: 50 | C2: =IF(A2="","",SUMIFS(Продажи!$C$2:$C$1000,Продажи!$B$2:$B$1000,A2)) | D2: =IF(A2="","",B2-C2) | E2: 10 | F2: =IF(OR(A2="",E2=""),"",IF(D2<E2,"Пора заказать",""))
A3: =IF(Товары!A3="","",Товары!A3) | B3: 40 | C3: =IF(A3="","",SUMIFS(Продажи!$C$2:$C$1000,Продажи!$B$2:$B$1000,A3)) | D3: =IF(A3="","",B3-C3) | E3: 10 | F3: =IF(OR(A3="",E3=""),"",IF(D3<E3,"Пора заказать",""))
A4: =IF(Товары!A4="","",Товары!A4) | B4: 30 | C4: =IF(A4="","",SUMIFS(Продажи!$C$2:$C$1000,Продажи!$B$2:$B$1000,A4)) | D4: =IF(A4="","",B4-C4) | E4: 5 | F4: =IF(OR(A4="",E4=""),"",IF(D4<E4,"Пора заказать",""))
A5: =IF(Товары!A5="","",Товары!A5) | C5: =IF(A5="","",SUMIFS(Продажи!$C$2:$C$1000,Продажи!$B$2:$B$1000,A5)) | D5: =IF(A5="","",B5-C5) | F5: =IF(OR(A5="",E5=""),"",IF(D5<E5,"Пора заказать",""))
A6: =IF(Товары!A6="","",Товары!A6) | C6: =IF(A6="","",SUMIFS(Продажи!$C$2:$C$1000,Продажи!$B$2:$B$1000,A6)) | D6: =IF(A6="","",B6-C6) | F6: =IF(OR(A6="",E6=""),"",IF(D6<E6,"Пора заказать",""))
A7: =IF(Товары!A7="","",Товары!A7) | C7: =IF(A7="","",SUMIFS(Продажи!$C$2:$C$1000,Продажи!$B$2:$B$1000,A7)) | D7: =IF(A7="","",B7-C7) | F7: =IF(OR(A7="",E7=""),"",IF(D7<E7,"Пора заказать",""))
A8: =IF(Товары!A8="","",Товары!A8) | C8: =IF(A8="","",SUMIFS(Продажи!$C$2:$C$1000,Продажи!$B$2:$B$1000,A8)) | D8: =IF(A8="","",B8-C8) | F8: =IF(OR(A8="",E8=""),"",IF(D8<E8,"Пора заказать",""))
A9: =IF(Товары!A9="","",Товары!A9) | C9: =IF(A9="","",SUMIFS(Продажи!$C$2:$C$1000,Продажи!$B$2:$B$1000,A9)) | D9: =IF(A9="","",B9-C9) | F9: =IF(OR(A9="",E9=""),"",IF(D9<E9,"Пора заказать",""))
A10: =IF(Товары!A10="","",Товары!A10) | C10: =IF(A10="","",SUMIFS(Продажи!$C$2:$C$1000,Продажи!$B$2:$B$1000,A10)) | D10: =IF(A10="","",B10-C10) | F10: =IF(OR(A10="",E10=""),"",IF(D10<E10,"Пора заказать",""))
A11: =IF(Товары!A11="","",Товары!A11) | C11: =IF(A11="","",SUMIFS(Продажи!$C$2:$C$1000,Продажи!$B$2:$B$1000,A11)) | D11: =IF(A11="","",B11-C11) | F11: =IF(OR(A11="",E11=""),"",IF(D11<E11,"Пора заказать",""))
A12: =IF(Товары!A12="","",Товары!A12) | C12: =IF(A12="","",SUMIFS(Продажи!$C$2:$C$1000,Продажи!$B$2:$B$1000,A12)) | D12: =IF(A12="","",B12-C12) | F12: =IF(OR(A12="",E12=""),"",IF(D12<E12,"Пора заказать",""))
A13: =IF(Товары!A13="","",Товары!A13) | C13: =IF(A13="","",SUMIFS(Продажи!$C$2:$C$1000,Продажи!$B$2:$B$1000,A13)) | D13: =IF(A13="","",B13-C13) | F13: =IF(OR(A13="",E13=""),"",IF(D13<E13,"Пора заказать",""))
A14: =IF(Товары!A14="","",Товары!A14) | C14: =IF(A14="","",SUMIFS(Продажи!$C$2:$C$1000,Продажи!$B$2:$B$1000,A14)) | D14: =IF(A14="","",B14-C14) | F14: =IF(OR(A14="",E14=""),"",IF(D14<E14,"Пора заказать",""))
A15: =IF(Товары!A15="","",Товары!A15) | C15: =IF(A15="","",SUMIFS(Продажи!$C$2:$C$1000,Продажи!$B$2:$B$1000,A15)) | D15: =IF(A15="","",B15-C15) | F15: =IF(OR(A15="",E15=""),"",IF(D15<E15,"Пора заказать",""))
A16: =IF(Товары!A16="","",Товары!A16) | C16: =IF(A16="","",SUMIFS(Продажи!$C$2:$C$1000,Продажи!$B$2:$B$1000,A16)) | D16: =IF(A16="","",B16-C16) | F16: =IF(OR(A16="",E16=""),"",IF(D16<E16,"Пора заказать",""))
... A51: =IF(Товары!A51="","",Товары!A51) | C51: =IF(A51="","",SUMIFS(Продажи!$C$2:$C$1000,Продажи!$B$2:$B$1000,A51)) | D51: =IF(A51="","",B51-C51) | F51: =IF(OR(A51="",E51=""),"",IF(D51<E51,"Пора заказать",""))

Sheet Итоги
A1: Итоги за месяц
A3: Месяц (ГГГГ-ММ) | B3: 2026-09
A4: Выручка | B4: =SUMIFS(Продажи!$E$2:$E$1000,Продажи!$G$2:$G$1000,$B$3)
A5: Прибыль (до рекламы и постоянных) | B5: =SUMIFS(Продажи!$F$2:$F$1000,Продажи!$G$2:$G$1000,$B$3)
A6: Продано штук (нетто) | B6: =SUMIFS(Продажи!$C$2:$C$1000,Продажи!$G$2:$G$1000,$B$3)
A7: Возвращено штук | B7: =-SUMIFS(Продажи!$C$2:$C$1000,Продажи!$G$2:$G$1000,$B$3,Продажи!$C$2:$C$1000,"<0")
A8: Реклама за месяц | B8: 15000
A9: Прочие постоянные за месяц | B9: 5000
A10: Чистая прибыль | B10: =B5-B8-B9
